feios/__init__.py
feios/__main__.py
feios/feios.py
feios-0.3.2.dist-info/LICENSE
feios-0.3.2.dist-info/METADATA
feios-0.3.2.dist-info/WHEEL
feios-0.3.2.dist-info/top_level.txt
feios-0.3.2.dist-info/RECORD
