Metadata-Version: 2.1
Name: feios
Version: 0.3.2
Summary: The feios main module
Home-page: https://github.com/devoter-fyc/fei-ros
Author: fyc
Author-email: fycsfls_winter@126.com
Project-URL: Bug Tracker, https://github.com/devoter-fyc/fei-ros/issues
Classifier: Programming Language :: Python :: 3
Classifier: License :: OSI Approved :: GNU General Public License v3 or later (GPLv3+)
Classifier: Operating System :: Microsoft :: Windows
Classifier: Operating System :: POSIX
Classifier: Development Status :: 5 - Production/Stable
Requires-Python: >=3.5
License-File: LICENSE
Requires-Dist: feios-utils (>=0.2.0b3)
